MANIFEST.in
README.txt
setup.cfg
setup.py
SaladeDeFruits.egg-info/PKG-INFO
SaladeDeFruits.egg-info/SOURCES.txt
SaladeDeFruits.egg-info/dependency_links.txt
SaladeDeFruits.egg-info/entry_points.txt
SaladeDeFruits.egg-info/not-zip-safe
SaladeDeFruits.egg-info/requires.txt
SaladeDeFruits.egg-info/top_level.txt
docs/index.txt
docs/salade.txt
docs/saladier.txt
saladedefruits/__init__.py
saladedefruits/rewrite.py
saladedefruits/salade.py
saladedefruits/saladier.py
saladedefruits/theme.html
saladedefruits/utils.py
saladedefruits/tests/__init__.py
saladedefruits/tests/test.css
saladedefruits/tests/test.html
saladedefruits/tests/test.js
saladedefruits/tests/tests.py
saladedefruits/tests/theme.html
saladedefruits/tests/user.html