Metadata-Version: 1.0
Name: SaladeDeFruits
Version: 0.7
Summary: A skinning middleware
Home-page: http://www.gawel.org/docs/SaladeDeFruits/index.html
Author: Gael Pasgrimaud
Author-email: gael@gawel.org
License: MIT
Keywords: wsgi middleware skin lxml pyquery
Platform: UNKNOWN
Classifier: Topic :: Internet :: WWW/HTTP :: WSGI :: Middleware
Classifier: Operating System :: OS Independent
